testbench.sv
// Code your testbench here
// or browse Examples
module PRPG(clk,load);

input clk;
input load;
output [2:0] din;
output [2:0] Q_out;
output Q1, Q2, Q3;

reg [2:0] din;
reg [2:0] Q_out;
reg Q1, Q2, Q3;
reg temp;

initial
begin
    temp = 0;
    Q1 = 1;
    Q2 = 0;
    Q3 = 0;
    Q_out = 3'b001;
    din = 3'b111;
end

  always@ (posedge clk or posedge load)
begin
  if(load)
    begin
        Q1 = din[0];
        Q2 = din[1];
        Q3 = din[2];
    end

    else
    begin
        temp = Q1;
        Q1 = Q1 ^ Q3;
        Q3 = Q2;
        Q2 = temp;
    end

    Q_out[0] = Q1;
    Q_out[1] = Q2;
    Q_out[2] = Q3;
end
endmodule

design.sv
// Code your design here

`timescale 1ns/1ps
module PRPG_tb;
reg clk_tb;
reg load_tb;
reg din_tb;

initial
begin
    clk_tb = 0;
    din_tb = 4;
    load_tb = 1'b0;
end

always
begin
    #10 clk_tb = ~clk_tb;
end

initial
begin
    #30 load_tb = 1'b0;
    #80 load_tb = 1'b1;
    #5 load_tb = 1'b0;
    #250 $finish;
end

initial
begin
    $dumpfile("PRPG.vcd");
    $dumpvars(0, PRPG_tb);
end

PRPG PRPG_tb
(
    .clk(clk_tb),
   .load(load_tb)
);
endmodule

PRPG.vcd
$date
	Mon Jun  6 02:20:16 2022
$end
$version
	Icarus Verilog
$end
$timescale
	1ps
$end
$scope module PRPG_tb $end
$scope module PRPG_tb $end
$var wire 1 ! clk $end
$var wire 1 " load $end
$var reg 1 # Q1 $end
$var reg 1 $ Q2 $end
$var reg 1 % Q3 $end
$var reg 3 & Q_out [2:0] $end
$var reg 3 ' din [2:0] $end
$var reg 1 ( temp $end
$upscope $end
$upscope $end
$enddefinitions $end
#0
$dumpvars
0(
b111 '
b1 &
0%
0$
1#
0"
0!
$end
#10000
b11 &
1$
1(
1!
#20000
0!
#30000
b111 &
1%
1!
#40000
0!
#50000
b110 &
0#
1!
#60000
0!
#70000
b101 &
0$
1#
0(
1!
#80000
0!
#90000
b10 &
1$
0%
0#
1(
1!
#100000
0!
#110000
b111 &
1%
1#
1!
1"
#115000
0"
#120000
0!
#130000
b110 &
0#
1!
#140000
0!
#150000
b101 &
0$
1#
0(
1!
#160000
0!
#170000
b10 &
1$
0%
0#
1(
1!
#180000
0!
#190000
b100 &
0$
1%
0(
1!
#200000
0!
#210000
b1 &
0%
1#
1!
#220000
0!
#230000
b11 &
1$
1(
1!
#240000
0!
#250000
b111 &
1%
1!
#260000
0!
#270000
b110 &
0#
1!
#280000
0!
#290000
b101 &
0$
1#
0(
1!
#300000
0!
#310000
b10 &
1$
0%
0#
1(
1!
#320000
0!
#330000
b100 &
0$
1%
0(
1!
#340000
0!
#350000
b1 &
0%
1#
1!
